enzyme_filtering_pipeline-0.0.41.data/data/LICENSE
enzyme_filtering_pipeline-0.0.41.dist-info/licenses/LICENSE
filtering_pipeline/__init__.py
filtering_pipeline/pipeline.py
filtering_pipeline/steps/PLACER_forChai_step.py
filtering_pipeline/steps/PLACER_forVina_step.py
filtering_pipeline/steps/__init__.py
filtering_pipeline/steps/cleanPDB_step.py
filtering_pipeline/steps/computeligandRMSD_step.py
filtering_pipeline/steps/computeproteinRMSD_step.py
filtering_pipeline/steps/extract_docking_metrics_step.py
filtering_pipeline/steps/fpocket_step.py
filtering_pipeline/steps/geometric_filtering.py
filtering_pipeline/steps/ligandSASA_step.py
filtering_pipeline/steps/plip_step.py
filtering_pipeline/steps/predict_catalyticsite_run.py
filtering_pipeline/steps/predict_catalyticsite_step.py
filtering_pipeline/steps/prepareaf3_step.py
filtering_pipeline/steps/prepareboltz_step.py
filtering_pipeline/steps/preparechai_step.py
filtering_pipeline/steps/prepareplacer_step.py
filtering_pipeline/steps/preparevina_step.py
filtering_pipeline/steps/retrieve_AF_structures_step.py
filtering_pipeline/steps/save_step.py
filtering_pipeline/steps/step.py
filtering_pipeline/steps/superimposestructures_step.py
filtering_pipeline/utils/__init__.py
filtering_pipeline/utils/helpers.py
enzyme_filtering_pipeline-0.0.41.dist-info/METADATA
enzyme_filtering_pipeline-0.0.41.dist-info/WHEEL
enzyme_filtering_pipeline-0.0.41.dist-info/entry_points.txt
enzyme_filtering_pipeline-0.0.41.dist-info/top_level.txt
enzyme_filtering_pipeline-0.0.41.dist-info/RECORD
