Metadata-Version: 2.4
Name: enzyme_filtering_pipeline
Version: 0.0.41
Home-page: https://github.com/HelenSchmid/EnzymeStructuralFiltering
Author: Helen Schmid
Author-email: schmid.helen2@gmail.com
License: GPL3
Project-URL: Bug Tracker, https://github.com/HelenSchmid/EnzymeStructuralFiltering/issues
Project-URL: Documentation, https://github.com/HelenSchmid/EnzymeStructuralFiltering
Project-URL: Source Code, https://github.com/HelenSchmid/EnzymeStructuralFiltering
Keywords: util
Classifier: Development Status :: 5 - Production/Stable
Classifier: Intended Audience :: Science/Research
Classifier: License :: OSI Approved :: GNU General Public License v3 (GPLv3)
Classifier: Natural Language :: English
Classifier: Operating System :: OS Independent
Classifier: Programming Language :: Python :: 3.6
Classifier: Programming Language :: Python :: 3.7
Classifier: Programming Language :: Python :: 3.8
Classifier: Topic :: Scientific/Engineering :: Bio-Informatics
Requires-Python: >=3.6
License-File: LICENSE
Requires-Dist: pandas
Requires-Dist: numpy
Requires-Dist: pybiomart
Dynamic: author
Dynamic: author-email
Dynamic: classifier
Dynamic: description
Dynamic: description-content-type
Dynamic: home-page
Dynamic: keywords
Dynamic: license
Dynamic: license-file
Dynamic: project-url
Dynamic: requires-dist
Dynamic: requires-python
